check_dependencies-0.12.6.dist-info/METADATA
check_dependencies-0.12.6.dist-info/WHEEL
check_dependencies-0.12.6.dist-info/entry_points.txt
check_dependencies-0.12.6.dist-info/licenses/LICENSE
check_dependencies/__init__.py
check_dependencies/__main__.py
check_dependencies/builtin_module.py
check_dependencies/lib.py
check_dependencies/main.py
tests/__init__.py
tests/conftest.py
tests/data/pyproject_cfg.toml
tests/data/pyproject_pep631.toml
tests/data/pyproject_pep631_extra.toml
tests/data/pyproject_poetry.toml
tests/data/pyproject_poetry_extra.toml
tests/data/src.py
tests/data/src2.py
tests/test_builtin_modules.py
tests/test_lib.py
tests/test_main.py
check_dependencies-0.12.6.dist-info/RECORD
