Metadata-Version: 2.1
Name: check-dependencies
Version: 0.12.6
Summary: Check dependencies of a python project against pyproject.toml requirements
Keywords: packaging,development,requirements,dependencies
Author-Email: Micha Scholl <schollm-git@gmx.com>
License: MIT
Classifier: Development Status :: 4 - Beta
Classifier: Intended Audience :: Developers
Classifier: License :: OSI Approved :: MIT License
Classifier: Programming Language :: Python :: 3
Classifier: Programming Language :: Python :: 3.8
Classifier: Programming Language :: Python :: 3.9
Classifier: Programming Language :: Python :: 3.10
Classifier: Programming Language :: Python :: 3.11
Classifier: Programming Language :: Python :: 3.12
Classifier: Programming Language :: Python :: Implementation :: CPython
Classifier: Programming Language :: Python :: Implementation :: PyPy
Classifier: Topic :: Software Development :: Quality Assurance
Classifier: Topic :: Software Development :: Testing
Classifier: Topic :: Utilities
Project-URL: Bug Tracker, https://github.com/schollm/check-dependencies/issues
Project-URL: homepage, https://github.com/schollm/check-dependencies
Project-URL: repository, https://github.com/schollm/check-dependencies
Project-URL: documentation, https://github.com/schollm/check-dependencies/blob/main/README.md
Requires-Python: >=3.8
Requires-Dist: toml; python_version < "3.11"
